{"46625": ["TCT477"], "46629": ["TCT477"], "46641": ["TCT321", "TCT407", "TCT421", "TCT477"], "46649": ["TCT321", "TCT407", "TCT421", "TCT477"], "46650": ["TCT477"], "46651": ["TCT321", "TCT407", "TCT421", "TCT477"], "46825": ["TCT321", "TCT407", "TCT477"], "46829": ["TCT321", "TCT407", "TCT421", "TCT477"], "46831": ["TCT321", "TCT407", "TCT421", "TCT477"], "46827": ["TCT321", "TCT407", "TCT421", "TCT477"], "46606": ["TCT321", "TCT407", "TCT421", "TCT477"], "46648": ["TCT321", "TCT407", "TCT421", "TCT477"], "65655": ["TCT321", "TCT407", "TCT421", "TCT477"], "46630": ["TCT477"], "46631": ["TCT477"], "46634": ["TCT477"], "46644": ["TCT477"]}